jupyter_slurm_ssh_provisioner/__init__.py
jupyter_slurm_ssh_provisioner/provisioner.py
jupyter_slurm_ssh_provisioner-0.2.0.dist-info/METADATA
jupyter_slurm_ssh_provisioner-0.2.0.dist-info/WHEEL
jupyter_slurm_ssh_provisioner-0.2.0.dist-info/entry_points.txt
jupyter_slurm_ssh_provisioner-0.2.0.dist-info/licenses/LICENSE
jupyter_slurm_ssh_provisioner-0.2.0.dist-info/RECORD
