Metadata-Version: 2.4
Name: jupyter_slurm_ssh_provisioner
Version: 0.2.0
Summary: Start a remote Kernel via ssh in a slurm job
Project-URL: Homepage, https://github.com/Ninichus/jupyter_slurm_ssh_provisioner
Project-URL: Issues, https://github.com/Ninichus/jupyter_slurm_ssh_provisioner/issues
Author-email: Arthur Conrozier <arthur.conrozier@hotmail.fr>
License-Expression: MIT
License-File: LICENSE
Requires-Dist: asyncssh
Requires-Dist: jupyter-client>=7.0.0
